forlib/__init__.py
forlib/calc_hash.py
forlib/decompress.py
forlib/decompress1.py
forlib/openAPI.py
forlib/signature.py
forlib/outcome/__init__.py
forlib/outcome/report.py
forlib/outcome/visualize.py
forlib/processing/__init__.py
forlib/processing/browser_analysis.py
forlib/processing/convert_time.py
forlib/processing/disk_analysis.py
forlib/processing/files_analysis.py
forlib/processing/filesystem_analysis.py
forlib/processing/filter.py
forlib/processing/iconcache_analysis.py
forlib/processing/jump_analysis.py
forlib/processing/lnk_analysis.py
forlib/processing/log_analysis.py
forlib/processing/mem_analysis.py
forlib/processing/prefetch_analysis.py
forlib/processing/recycle_analysis.py
forlib/processing/reg_analysis.py
forlib/processing/thumbnail_analysis.py
forlib/processing/winsearch_analysis.py
forlib/processing/internal/__init__.py
forlib/processing/internal/check.py
fortools/__init__.py
fortools/chatbot.py
fortools/toplevel.py
fortools-0.0.10.dist-info/METADATA
fortools-0.0.10.dist-info/WHEEL
fortools-0.0.10.dist-info/top_level.txt
fortools-0.0.10.dist-info/RECORD
