Metadata-Version: 2.1
Name: fortools
Version: 0.0.10
Summary: forensics python library fortools
Home-page: https://github.com/5ha0/fortools/fortools
Author: 5ha0
Author-email: fortools.official@gmail.com
License: UNKNOWN
Download-URL: https://github.com/5ha0/fortools/archive/master.zip
Platform: UNKNOWN
Classifier: Programming Language :: Python :: 3
Requires-Python: >3.5
Requires-Dist: bitstring
Requires-Dist: chardet
Requires-Dist: image
Requires-Dist: libesedb-python
Requires-Dist: libevtx-python
Requires-Dist: libewf-python
Requires-Dist: lxml
Requires-Dist: matplotlib
Requires-Dist: numpy
Requires-Dist: olefile
Requires-Dist: PyPDF2
Requires-Dist: python-docx
Requires-Dist: python-magic
Requires-Dist: python-magic-bin
Requires-Dist: python-registry
Requires-Dist: pytsk3
Requires-Dist: xmltodict
